{
  "name": "Academy of Magic Ground Floor",
  "width": 4800,
  "height": 4050,
  "grid": 150,
  "shiftX": 0,
  "shiftY": 0,
  "gridDistance": 5.0,
  "gridUnits": "ft",
  "padding": 0.0,
  "gridColor": "#000000",
  "gridAlpha": 0.2,
  "globalLight": true,
  "darkness": 0.3,
  "lights": [
    {
      "x": 658,
      "y": 968,
      "dim": 25.0,
      "bright": 12.5,
      "tintColor": "#FFAD40",
      "tintAlpha": 0.0
    },
    {
      "x": 1143,
      "y": 3022,
      "dim": 20.0,
      "bright": 10.0,
      "tintColor": "#FFAD40",
      "tintAlpha": 0.0
    },
    {
      "x": 961,
      "y": 3036,
      "dim": 20.0,
      "bright": 10.0,
      "tintColor": "#FFAD40",
      "tintAlpha": 0.0
    },
    {
      "x": 688,
      "y": 2527,
      "dim": 25.0,
      "bright": 12.5,
      "tintColor": "#FFAD40",
      "tintAlpha": 0.0
    },
    {
      "x": 841,
      "y": 2764,
      "dim": 10.0,
      "bright": 5.0,
      "tintColor": "#FFAD40",
      "tintAlpha": 0.0
    },
    {
      "x": 1267,
      "y": 2764,
      "dim": 10.0,
      "bright": 5.0,
      "tintColor": "#FFAD40",
      "tintAlpha": 0.0
    },
    {
      "x": 1261,
      "y": 2484,
      "dim": 10.0,
      "bright": 5.0,
      "tintColor": "#FFAD40",
      "tintAlpha": 0.0
    },
    {
      "x": 846,
      "y": 2434,
      "dim": 10.0,
      "bright": 5.0,
      "tintColor": "#FFAD40",
      "tintAlpha": 0.0
    },
    {
      "x": 853,
      "y": 2191,
      "dim": 10.0,
      "bright": 5.0,
      "tintColor": "#FFAD40",
      "tintAlpha": 0.0
    },
    {
      "x": 1239,
      "y": 2201,
      "dim": 10.0,
      "bright": 5.0,
      "tintColor": "#FFAD40",
      "tintAlpha": 0.0
    },
    {
      "x": 1915,
      "y": 3080,
      "dim": 20.0,
      "bright": 10.0,
      "tintColor": "#FFC140",
      "tintAlpha": 0.0
    },
    {
      "x": 2254,
      "y": 795,
      "dim": 25.0,
      "bright": 12.5,
      "tintColor": "#FFAD40",
      "tintAlpha": 0.0
    },
    {
      "x": 1568,
      "y": 768,
      "dim": 25.0,
      "bright": 12.5,
      "tintColor": "#FFA528",
      "tintAlpha": 0.0
    },
    {
      "x": 2881,
      "y": 1006,
      "dim": 20.0,
      "bright": 10.0,
      "tintColor": "#FFAD40",
      "tintAlpha": 0.0
    },
    {
      "x": 2111,
      "y": 1103,
      "dim": 20.0,
      "bright": 10.0,
      "tintColor": "#FFAD40",
      "tintAlpha": 0.0
    },
    {
      "x": 1617,
      "y": 1161,
      "dim": 20.0,
      "bright": 10.0,
      "tintColor": "#FFAD40",
      "tintAlpha": 0.0
    },
    {
      "x": 3274,
      "y": 818,
      "dim": 20.0,
      "bright": 10.0,
      "tintColor": "#FFAD40",
      "tintAlpha": 0.0
    },
    {
      "x": 3274,
      "y": 1119,
      "dim": 20.0,
      "bright": 10.0,
      "tintColor": "#FFAD40",
      "tintAlpha": 0.0
    },
    {
      "x": 3332,
      "y": 1274,
      "dim": 20.0,
      "bright": 10.0,
      "tintColor": "#FFAD40",
      "tintAlpha": 0.0
    },
    {
      "x": 3677,
      "y": 1907,
      "dim": 25.0,
      "bright": 12.5,
      "tintColor": "#FF9800",
      "tintAlpha": 0.0
    },
    {
      "x": 3500,
      "y": 2029,
      "dim": 25.0,
      "bright": 12.5,
      "tintColor": "#FF9800",
      "tintAlpha": 0.0
    },
    {
      "x": 3332,
      "y": 2929,
      "dim": 20.0,
      "bright": 10.0,
      "tintColor": "#FFAD40",
      "tintAlpha": 0.0
    },
    {
      "x": 3864,
      "y": 3498,
      "dim": 20.0,
      "bright": 10.0,
      "tintColor": "#00CADD",
      "tintAlpha": 0.0
    },
    {
      "x": 4247,
      "y": 3108,
      "dim": 20.0,
      "bright": 10.0,
      "tintColor": "#00CADD",
      "tintAlpha": 0.0
    },
    {
      "x": 786,
      "y": 399,
      "dim": 20.0,
      "bright": 10.0,
      "tintColor": "#FFAD40",
      "tintAlpha": 0.0
    },
    {
      "x": 402,
      "y": 789,
      "dim": 20.0,
      "bright": 10.0,
      "tintColor": "#FFAD40",
      "tintAlpha": 0.0
    },
    {
      "x": 3832,
      "y": 1614,
      "dim": 20.0,
      "bright": 10.0,
      "tintColor": "#FFC140",
      "tintAlpha": 0.0
    },
    {
      "x": 4150,
      "y": 615,
      "dim": 20.0,
      "bright": 10.0,
      "tintColor": "#FFAD40",
      "tintAlpha": 0.0
    },
    {
      "x": 3935,
      "y": 2829,
      "dim": 3.996332,
      "bright": 1.998166,
      "tintColor": "#47EAFF",
      "tintAlpha": 0.0
    },
    {
      "x": 4503,
      "y": 2033,
      "dim": 20.0,
      "bright": 10.0,
      "tintColor": "#FFAD40",
      "tintAlpha": 0.0
    },
    {
      "x": 4494,
      "y": 1577,
      "dim": 20.0,
      "bright": 10.0,
      "tintColor": "#FFAD40",
      "tintAlpha": 0.0
    },
    {
      "x": 4027,
      "y": 1269,
      "dim": 20.0,
      "bright": 10.0,
      "tintColor": "#FFAD40",
      "tintAlpha": 0.0
    },
    {
      "x": 4251,
      "y": 3495,
      "dim": 20.0,
      "bright": 10.0,
      "tintColor": "#00CADD",
      "tintAlpha": 0.0
    },
    {
      "x": 2881,
      "y": 3080,
      "dim": 20.0,
      "bright": 10.0,
      "tintColor": "#FFAD00",
      "tintAlpha": 0.0
    },
    {
      "x": 1984,
      "y": 3076,
      "dim": 22.3560219,
      "bright": 11.1780109,
      "tintColor": "#FFB055",
      "tintAlpha": 0.0
    },
    {
      "x": 2436,
      "y": 3076,
      "dim": 22.3560219,
      "bright": 11.1780109,
      "tintColor": "#FFB055",
      "tintAlpha": 0.0
    },
    {
      "x": 525,
      "y": 3568,
      "dim": 20.0,
      "bright": 10.0,
      "tintColor": "#FFAD40",
      "tintAlpha": 0.0
    },
    {
      "x": 399,
      "y": 3112,
      "dim": 20.0,
      "bright": 10.0,
      "tintColor": "#FFAD40",
      "tintAlpha": 0.0
    },
    {
      "x": 628,
      "y": 2171,
      "dim": 20.0,
      "bright": 10.0,
      "tintColor": "#FFB055",
      "tintAlpha": 0.0
    },
    {
      "x": 822,
      "y": 1919,
      "dim": 20.0,
      "bright": 10.0,
      "tintColor": "#FFAD40",
      "tintAlpha": 0.0
    },
    {
      "x": 1468,
      "y": 667,
      "dim": 20.0,
      "bright": 10.0,
      "tintColor": "#FFAD40",
      "tintAlpha": 0.0
    },
    {
      "x": 1468,
      "y": 1871,
      "dim": 20.0,
      "bright": 10.0,
      "tintColor": "#FFAD40",
      "tintAlpha": 0.0
    },
    {
      "x": 3982,
      "y": 331,
      "dim": 20.0,
      "bright": 10.0,
      "tintColor": "#FFAD40",
      "tintAlpha": 0.0
    },
    {
      "x": 4321,
      "y": 663,
      "dim": 20.0,
      "bright": 10.0,
      "tintColor": "#FFAD40",
      "tintAlpha": 0.0
    }
  ],
  "walls": [
    {
      "c": [
        591,
        3004,
        591,
        2853
      ],
      "move": 1,
      "sense": 1,
      "sound": 1,
      "door": 0
    },
    {
      "c": [
        591,
        2853,
        591,
        2250
      ],
      "move": 1,
      "sense": 0,
      "sound": 1,
      "door": 0
    },
    {
      "c": [
        591,
        2250,
        591,
        1949
      ],
      "move": 1,
      "sense": 1,
      "sound": 1,
      "door": 0
    },
    {
      "c": [
        591,
        1949,
        1496,
        1949
      ],
      "move": 1,
      "sense": 1,
      "sound": 1,
      "door": 0
    },
    {
      "c": [
        591,
        1949,
        591,
        1346
      ],
      "move": 1,
      "sense": 1,
      "sound": 1,
      "door": 0
    },
    {
      "c": [
        591,
        1044,
        591,
        1346
      ],
      "move": 1,
      "sense": 0,
      "sound": 1,
      "door": 0
    },
    {
      "c": [
        591,
        1044,
        591,
        893
      ],
      "move": 1,
      "sense": 1,
      "sound": 1,
      "door": 0
    },
    {
      "c": [
        893,
        3305,
        1646,
        3305
      ],
      "move": 1,
      "sense": 1,
      "sound": 1,
      "door": 0
    },
    {
      "c": [
        893,
        592,
        1496,
        592
      ],
      "move": 1,
      "sense": 1,
      "sound": 1,
      "door": 0
    },
    {
      "c": [
        1496,
        3305,
        1496,
        3155
      ],
      "move": 1,
      "sense": 1,
      "sound": 1,
      "door": 1
    },
    {
      "c": [
        1496,
        3155,
        1496,
        2853
      ],
      "move": 1,
      "sense": 1,
      "sound": 1,
      "door": 0
    },
    {
      "c": [
        1496,
        2853,
        1948,
        2853
      ],
      "move": 1,
      "sense": 1,
      "sound": 1,
      "door": 0
    },
    {
      "c": [
        1496,
        2853,
        1496,
        2702
      ],
      "move": 1,
      "sense": 1,
      "sound": 1,
      "door": 0
    },
    {
      "c": [
        1496,
        2702,
        1496,
        2401
      ],
      "move": 1,
      "sense": 0,
      "sound": 1,
      "door": 0
    },
    {
      "c": [
        1496,
        2401,
        1496,
        2250
      ],
      "move": 1,
      "sense": 1,
      "sound": 1,
      "door": 0
    },
    {
      "c": [
        1496,
        2250,
        1496,
        2099
      ],
      "move": 1,
      "sense": 1,
      "sound": 1,
      "door": 1
    },
    {
      "c": [
        1496,
        2099,
        1496,
        1949
      ],
      "move": 1,
      "sense": 1,
      "sound": 1,
      "door": 0
    },
    {
      "c": [
        1496,
        1949,
        1496,
        1798
      ],
      "move": 1,
      "sense": 1,
      "sound": 1,
      "door": 0
    },
    {
      "c": [
        1496,
        1798,
        1496,
        1496
      ],
      "move": 1,
      "sense": 0,
      "sound": 1,
      "door": 0
    },
    {
      "c": [
        1496,
        1496,
        1496,
        1346
      ],
      "move": 1,
      "sense": 1,
      "sound": 1,
      "door": 1
    },
    {
      "c": [
        1496,
        1346,
        1646,
        1346
      ],
      "move": 1,
      "sense": 1,
      "sound": 1,
      "door": 0
    },
    {
      "c": [
        1496,
        1346,
        1496,
        592
      ],
      "move": 1,
      "sense": 1,
      "sound": 1,
      "door": 0
    },
    {
      "c": [
        1496,
        592,
        1797,
        592
      ],
      "move": 1,
      "sense": 1,
      "sound": 1,
      "door": 0
    },
    {
      "c": [
        1646,
        3305,
        1797,
        3305
      ],
      "move": 1,
      "sense": 0,
      "sound": 1,
      "door": 0
    },
    {
      "c": [
        1948,
        1346,
        1646,
        1346
      ],
      "move": 1,
      "sense": 0,
      "sound": 1,
      "door": 0
    },
    {
      "c": [
        1948,
        3305,
        1797,
        3305
      ],
      "move": 1,
      "sense": 1,
      "sound": 1,
      "door": 0
    },
    {
      "c": [
        1797,
        2552,
        1797,
        1647
      ],
      "move": 1,
      "sense": 0,
      "sound": 1,
      "door": 0
    },
    {
      "c": [
        1797,
        2552,
        3154,
        2552
      ],
      "move": 1,
      "sense": 0,
      "sound": 1,
      "door": 0
    },
    {
      "c": [
        1797,
        1647,
        3154,
        1647
      ],
      "move": 1,
      "sense": 0,
      "sound": 1,
      "door": 0
    },
    {
      "c": [
        1797,
        592,
        1948,
        592
      ],
      "move": 1,
      "sense": 0,
      "sound": 1,
      "door": 0
    },
    {
      "c": [
        1948,
        3305,
        1948,
        2853
      ],
      "move": 1,
      "sense": 1,
      "sound": 1,
      "door": 0
    },
    {
      "c": [
        2099,
        3305,
        1948,
        3305
      ],
      "move": 1,
      "sense": 0,
      "sound": 1,
      "door": 0
    },
    {
      "c": [
        1948,
        2853,
        2099,
        2853
      ],
      "move": 1,
      "sense": 1,
      "sound": 1,
      "door": 1
    },
    {
      "c": [
        1948,
        1346,
        2099,
        1346
      ],
      "move": 1,
      "sense": 1,
      "sound": 1,
      "door": 0
    },
    {
      "c": [
        1948,
        592,
        2099,
        592
      ],
      "move": 1,
      "sense": 1,
      "sound": 1,
      "door": 0
    },
    {
      "c": [
        2099,
        3305,
        2400,
        3305
      ],
      "move": 1,
      "sense": 1,
      "sound": 1,
      "door": 0
    },
    {
      "c": [
        2099,
        2853,
        2400,
        2853
      ],
      "move": 1,
      "sense": 1,
      "sound": 1,
      "door": 0
    },
    {
      "c": [
        2249,
        1346,
        2099,
        1346
      ],
      "move": 1,
      "sense": 1,
      "sound": 1,
      "door": 1
    },
    {
      "c": [
        2099,
        592,
        2249,
        592
      ],
      "move": 1,
      "sense": 0,
      "sound": 1,
      "door": 0
    },
    {
      "c": [
        2249,
        1346,
        2400,
        1346
      ],
      "move": 1,
      "sense": 1,
      "sound": 1,
      "door": 0
    },
    {
      "c": [
        2249,
        592,
        2400,
        592
      ],
      "move": 1,
      "sense": 1,
      "sound": 1,
      "door": 0
    },
    {
      "c": [
        2400,
        3305,
        2400,
        2853
      ],
      "move": 1,
      "sense": 1,
      "sound": 1,
      "door": 0
    },
    {
      "c": [
        2400,
        3305,
        2701,
        3305
      ],
      "move": 1,
      "sense": 1,
      "sound": 1,
      "door": 0
    },
    {
      "c": [
        2400,
        2853,
        2551,
        2853
      ],
      "move": 1,
      "sense": 1,
      "sound": 1,
      "door": 1
    },
    {
      "c": [
        2400,
        2249,
        2700,
        2249
      ],
      "move": 1,
      "sense": 0,
      "sound": 1,
      "door": 0
    },
    {
      "c": [
        2400,
        2249,
        2400,
        1949
      ],
      "move": 1,
      "sense": 0,
      "sound": 1,
      "door": 0
    },
    {
      "c": [
        2400,
        1949,
        2700,
        1949
      ],
      "move": 1,
      "sense": 0,
      "sound": 1,
      "door": 0
    },
    {
      "c": [
        2701,
        1346,
        2400,
        1346
      ],
      "move": 1,
      "sense": 0,
      "sound": 1,
      "door": 0
    },
    {
      "c": [
        2400,
        592,
        2551,
        592
      ],
      "move": 1,
      "sense": 0,
      "sound": 1,
      "door": 0
    },
    {
      "c": [
        2551,
        2853,
        2852,
        2853
      ],
      "move": 1,
      "sense": 1,
      "sound": 1,
      "door": 0
    },
    {
      "c": [
        2551,
        592,
        2701,
        592
      ],
      "move": 1,
      "sense": 1,
      "sound": 1,
      "door": 0
    },
    {
      "c": [
        2852,
        3305,
        2701,
        3305
      ],
      "move": 1,
      "sense": 0,
      "sound": 1,
      "door": 0
    },
    {
      "c": [
        2700,
        2249,
        2700,
        1949
      ],
      "move": 1,
      "sense": 0,
      "sound": 1,
      "door": 0
    },
    {
      "c": [
        2701,
        1346,
        3003,
        1346
      ],
      "move": 1,
      "sense": 1,
      "sound": 1,
      "door": 0
    },
    {
      "c": [
        2701,
        592,
        2852,
        592
      ],
      "move": 1,
      "sense": 0,
      "sound": 1,
      "door": 0
    },
    {
      "c": [
        2852,
        3305,
        2852,
        2853
      ],
      "move": 1,
      "sense": 1,
      "sound": 1,
      "door": 0
    },
    {
      "c": [
        2852,
        3305,
        3003,
        3305
      ],
      "move": 1,
      "sense": 1,
      "sound": 1,
      "door": 0
    },
    {
      "c": [
        2852,
        2853,
        3003,
        2853
      ],
      "move": 1,
      "sense": 1,
      "sound": 1,
      "door": 0
    },
    {
      "c": [
        2852,
        592,
        3003,
        592
      ],
      "move": 1,
      "sense": 1,
      "sound": 1,
      "door": 0
    },
    {
      "c": [
        3003,
        3305,
        3154,
        3305
      ],
      "move": 1,
      "sense": 0,
      "sound": 1,
      "door": 0
    },
    {
      "c": [
        3154,
        1346,
        3003,
        1346
      ],
      "move": 1,
      "sense": 0,
      "sound": 1,
      "door": 0
    },
    {
      "c": [
        3003,
        592,
        3154,
        592
      ],
      "move": 1,
      "sense": 0,
      "sound": 1,
      "door": 0
    },
    {
      "c": [
        3154,
        3305,
        3304,
        3305
      ],
      "move": 1,
      "sense": 1,
      "sound": 1,
      "door": 0
    },
    {
      "c": [
        3154,
        2552,
        3154,
        1647
      ],
      "move": 1,
      "sense": 0,
      "sound": 1,
      "door": 0
    },
    {
      "c": [
        3154,
        1346,
        3304,
        1346
      ],
      "move": 1,
      "sense": 1,
      "sound": 1,
      "door": 0
    },
    {
      "c": [
        3154,
        592,
        3304,
        592
      ],
      "move": 1,
      "sense": 1,
      "sound": 1,
      "door": 0
    },
    {
      "c": [
        3304,
        3305,
        3304,
        2853
      ],
      "move": 1,
      "sense": 1,
      "sound": 1,
      "door": 0
    },
    {
      "c": [
        3455,
        3305,
        3304,
        3305
      ],
      "move": 1,
      "sense": 1,
      "sound": 1,
      "door": 0
    },
    {
      "c": [
        3304,
        2853,
        3455,
        2853
      ],
      "move": 1,
      "sense": 1,
      "sound": 1,
      "door": 0
    },
    {
      "c": [
        3455,
        1346,
        3304,
        1346
      ],
      "move": 1,
      "sense": 1,
      "sound": 1,
      "door": 1
    },
    {
      "c": [
        3304,
        1346,
        3304,
        592
      ],
      "move": 1,
      "sense": 1,
      "sound": 1,
      "door": 0
    },
    {
      "c": [
        3304,
        592,
        3606,
        592
      ],
      "move": 1,
      "sense": 1,
      "sound": 1,
      "door": 0
    },
    {
      "c": [
        3455,
        3305,
        3606,
        3305
      ],
      "move": 1,
      "sense": 0,
      "sound": 1,
      "door": 0
    },
    {
      "c": [
        3455,
        2853,
        3455,
        2702
      ],
      "move": 1,
      "sense": 1,
      "sound": 1,
      "door": 1
    },
    {
      "c": [
        3455,
        2702,
        3455,
        2401
      ],
      "move": 1,
      "sense": 1,
      "sound": 1,
      "door": 0
    },
    {
      "c": [
        3455,
        2702,
        4058,
        2702
      ],
      "move": 1,
      "sense": 1,
      "sound": 1,
      "door": 0
    },
    {
      "c": [
        3455,
        2401,
        3455,
        2250
      ],
      "move": 1,
      "sense": 1,
      "sound": 1,
      "door": 1
    },
    {
      "c": [
        3455,
        2250,
        3455,
        1949
      ],
      "move": 1,
      "sense": 1,
      "sound": 1,
      "door": 0
    },
    {
      "c": [
        3455,
        1949,
        4058,
        1949
      ],
      "move": 1,
      "sense": 1,
      "sound": 1,
      "door": 0
    },
    {
      "c": [
        3455,
        1647,
        4058,
        1647
      ],
      "move": 1,
      "sense": 1,
      "sound": 1,
      "door": 0
    },
    {
      "c": [
        3455,
        1647,
        3455,
        1496
      ],
      "move": 1,
      "sense": 1,
      "sound": 1,
      "door": 1
    },
    {
      "c": [
        3455,
        1496,
        3455,
        1346
      ],
      "move": 1,
      "sense": 1,
      "sound": 1,
      "door": 0
    },
    {
      "c": [
        3455,
        1346,
        4058,
        1346
      ],
      "move": 1,
      "sense": 1,
      "sound": 1,
      "door": 0
    },
    {
      "c": [
        3606,
        3305,
        3757,
        3305
      ],
      "move": 1,
      "sense": 1,
      "sound": 1,
      "door": 0
    },
    {
      "c": [
        3606,
        592,
        3757,
        592
      ],
      "move": 1,
      "sense": 0,
      "sound": 1,
      "door": 0
    },
    {
      "c": [
        4058,
        3004,
        4058,
        2853
      ],
      "move": 1,
      "sense": 0,
      "sound": 1,
      "door": 0
    },
    {
      "c": [
        4058,
        2853,
        4058,
        2702
      ],
      "move": 1,
      "sense": 1,
      "sound": 1,
      "door": 0
    },
    {
      "c": [
        4058,
        2702,
        4058,
        2401
      ],
      "move": 1,
      "sense": 0,
      "sound": 1,
      "door": 0
    },
    {
      "c": [
        4058,
        2401,
        4058,
        2250
      ],
      "move": 1,
      "sense": 1,
      "sound": 1,
      "door": 0
    },
    {
      "c": [
        4058,
        2250,
        4058,
        1949
      ],
      "move": 1,
      "sense": 0,
      "sound": 1,
      "door": 0
    },
    {
      "c": [
        4058,
        1949,
        4058,
        1647
      ],
      "move": 1,
      "sense": 1,
      "sound": 1,
      "door": 1
    },
    {
      "c": [
        4058,
        1346,
        4058,
        1044
      ],
      "move": 1,
      "sense": 1,
      "sound": 1,
      "door": 0
    },
    {
      "c": [
        4058,
        1044,
        4058,
        893
      ],
      "move": 1,
      "sense": 0,
      "sound": 1,
      "door": 0
    },
    {
      "c": [
        584,
        3610,
        677,
        3598
      ],
      "move": 1,
      "sense": 1,
      "sound": 1,
      "door": 0
    },
    {
      "c": [
        663,
        3602,
        750,
        3566
      ],
      "move": 1,
      "sense": 1,
      "sound": 1,
      "door": 0
    },
    {
      "c": [
        738,
        3573,
        812,
        3516
      ],
      "move": 1,
      "sense": 1,
      "sound": 1,
      "door": 0
    },
    {
      "c": [
        802,
        3526,
        859,
        3452
      ],
      "move": 1,
      "sense": 1,
      "sound": 1,
      "door": 0
    },
    {
      "c": [
        852,
        3464,
        888,
        3377
      ],
      "move": 1,
      "sense": 1,
      "sound": 1,
      "door": 0
    },
    {
      "c": [
        884,
        3391,
        896,
        3298
      ],
      "move": 1,
      "sense": 1,
      "sound": 1,
      "door": 0
    },
    {
      "c": [
        286,
        3298,
        298,
        3391
      ],
      "move": 1,
      "sense": 1,
      "sound": 1,
      "door": 0
    },
    {
      "c": [
        295,
        3377,
        330,
        3464
      ],
      "move": 1,
      "sense": 1,
      "sound": 1,
      "door": 0
    },
    {
      "c": [
        323,
        3452,
        380,
        3526
      ],
      "move": 1,
      "sense": 1,
      "sound": 1,
      "door": 0
    },
    {
      "c": [
        371,
        3516,
        445,
        3573
      ],
      "move": 1,
      "sense": 1,
      "sound": 1,
      "door": 0
    },
    {
      "c": [
        433,
        3566,
        519,
        3602
      ],
      "move": 1,
      "sense": 1,
      "sound": 1,
      "door": 0
    },
    {
      "c": [
        505,
        3598,
        598,
        3610
      ],
      "move": 1,
      "sense": 1,
      "sound": 1,
      "door": 0
    },
    {
      "c": [
        598,
        3000,
        505,
        3012
      ],
      "move": 1,
      "sense": 1,
      "sound": 1,
      "door": 0
    },
    {
      "c": [
        519,
        3009,
        433,
        3045
      ],
      "move": 1,
      "sense": 1,
      "sound": 1,
      "door": 0
    },
    {
      "c": [
        445,
        3038,
        371,
        3095
      ],
      "move": 1,
      "sense": 1,
      "sound": 1,
      "door": 0
    },
    {
      "c": [
        380,
        3085,
        323,
        3159
      ],
      "move": 1,
      "sense": 1,
      "sound": 1,
      "door": 0
    },
    {
      "c": [
        330,
        3147,
        295,
        3233
      ],
      "move": 1,
      "sense": 1,
      "sound": 1,
      "door": 0
    },
    {
      "c": [
        298,
        3220,
        286,
        3312
      ],
      "move": 1,
      "sense": 1,
      "sound": 1,
      "door": 0
    },
    {
      "c": [
        4363,
        3312,
        4351,
        3220
      ],
      "move": 1,
      "sense": 1,
      "sound": 1,
      "door": 0
    },
    {
      "c": [
        4355,
        3233,
        4319,
        3147
      ],
      "move": 1,
      "sense": 1,
      "sound": 1,
      "door": 0
    },
    {
      "c": [
        4326,
        3159,
        4269,
        3085
      ],
      "move": 1,
      "sense": 1,
      "sound": 1,
      "door": 0
    },
    {
      "c": [
        4279,
        3095,
        4205,
        3038
      ],
      "move": 1,
      "sense": 1,
      "sound": 1,
      "door": 0
    },
    {
      "c": [
        4217,
        3045,
        4130,
        3009
      ],
      "move": 1,
      "sense": 1,
      "sound": 1,
      "door": 0
    },
    {
      "c": [
        4144,
        3012,
        4051,
        3000
      ],
      "move": 1,
      "sense": 1,
      "sound": 1,
      "door": 0
    },
    {
      "c": [
        4051,
        3610,
        4144,
        3598
      ],
      "move": 1,
      "sense": 1,
      "sound": 1,
      "door": 0
    },
    {
      "c": [
        4130,
        3602,
        4217,
        3566
      ],
      "move": 1,
      "sense": 1,
      "sound": 1,
      "door": 0
    },
    {
      "c": [
        4205,
        3573,
        4279,
        3516
      ],
      "move": 1,
      "sense": 1,
      "sound": 1,
      "door": 0
    },
    {
      "c": [
        4269,
        3526,
        4326,
        3452
      ],
      "move": 1,
      "sense": 1,
      "sound": 1,
      "door": 0
    },
    {
      "c": [
        4319,
        3464,
        4355,
        3377
      ],
      "move": 1,
      "sense": 1,
      "sound": 1,
      "door": 0
    },
    {
      "c": [
        4351,
        3391,
        4363,
        3298
      ],
      "move": 1,
      "sense": 1,
      "sound": 1,
      "door": 0
    },
    {
      "c": [
        3753,
        3298,
        3765,
        3391
      ],
      "move": 1,
      "sense": 1,
      "sound": 1,
      "door": 0
    },
    {
      "c": [
        3762,
        3377,
        3797,
        3464
      ],
      "move": 1,
      "sense": 1,
      "sound": 1,
      "door": 0
    },
    {
      "c": [
        3791,
        3452,
        3847,
        3526
      ],
      "move": 1,
      "sense": 1,
      "sound": 1,
      "door": 0
    },
    {
      "c": [
        3838,
        3516,
        3912,
        3573
      ],
      "move": 1,
      "sense": 1,
      "sound": 1,
      "door": 0
    },
    {
      "c": [
        3900,
        3566,
        3986,
        3602
      ],
      "move": 1,
      "sense": 1,
      "sound": 1,
      "door": 0
    },
    {
      "c": [
        3972,
        3598,
        4065,
        3610
      ],
      "move": 1,
      "sense": 1,
      "sound": 1,
      "door": 0
    },
    {
      "c": [
        286,
        585,
        298,
        678
      ],
      "move": 1,
      "sense": 1,
      "sound": 1,
      "door": 0
    },
    {
      "c": [
        295,
        664,
        330,
        750
      ],
      "move": 1,
      "sense": 1,
      "sound": 1,
      "door": 0
    },
    {
      "c": [
        323,
        738,
        380,
        813
      ],
      "move": 1,
      "sense": 1,
      "sound": 1,
      "door": 0
    },
    {
      "c": [
        370,
        803,
        445,
        860
      ],
      "move": 1,
      "sense": 1,
      "sound": 1,
      "door": 0
    },
    {
      "c": [
        433,
        853,
        519,
        888
      ],
      "move": 1,
      "sense": 1,
      "sound": 1,
      "door": 0
    },
    {
      "c": [
        505,
        885,
        598,
        897
      ],
      "move": 1,
      "sense": 1,
      "sound": 1,
      "door": 0
    },
    {
      "c": [
        598,
        287,
        505,
        299
      ],
      "move": 1,
      "sense": 1,
      "sound": 1,
      "door": 0
    },
    {
      "c": [
        519,
        296,
        433,
        331
      ],
      "move": 1,
      "sense": 1,
      "sound": 1,
      "door": 0
    },
    {
      "c": [
        445,
        324,
        371,
        381
      ],
      "move": 1,
      "sense": 1,
      "sound": 1,
      "door": 0
    },
    {
      "c": [
        380,
        371,
        323,
        446
      ],
      "move": 1,
      "sense": 1,
      "sound": 1,
      "door": 0
    },
    {
      "c": [
        330,
        433,
        295,
        520
      ],
      "move": 1,
      "sense": 1,
      "sound": 1,
      "door": 0
    },
    {
      "c": [
        298,
        506,
        286,
        599
      ],
      "move": 1,
      "sense": 1,
      "sound": 1,
      "door": 0
    },
    {
      "c": [
        896,
        599,
        884,
        506
      ],
      "move": 1,
      "sense": 1,
      "sound": 1,
      "door": 0
    },
    {
      "c": [
        888,
        520,
        852,
        433
      ],
      "move": 1,
      "sense": 1,
      "sound": 1,
      "door": 0
    },
    {
      "c": [
        859,
        446,
        802,
        371
      ],
      "move": 1,
      "sense": 1,
      "sound": 1,
      "door": 0
    },
    {
      "c": [
        812,
        381,
        738,
        324
      ],
      "move": 1,
      "sense": 1,
      "sound": 1,
      "door": 0
    },
    {
      "c": [
        750,
        331,
        663,
        296
      ],
      "move": 1,
      "sense": 1,
      "sound": 1,
      "door": 0
    },
    {
      "c": [
        677,
        299,
        584,
        287
      ],
      "move": 1,
      "sense": 1,
      "sound": 1,
      "door": 0
    },
    {
      "c": [
        4211,
        1503,
        4204,
        1451
      ],
      "move": 1,
      "sense": 1,
      "sound": 1,
      "door": 0
    },
    {
      "c": [
        4208,
        1463,
        4187,
        1414
      ],
      "move": 1,
      "sense": 1,
      "sound": 1,
      "door": 0
    },
    {
      "c": [
        4194,
        1426,
        4162,
        1384
      ],
      "move": 1,
      "sense": 1,
      "sound": 1,
      "door": 0
    },
    {
      "c": [
        4171,
        1393,
        4129,
        1361
      ],
      "move": 1,
      "sense": 1,
      "sound": 1,
      "door": 0
    },
    {
      "c": [
        4140,
        1367,
        4091,
        1347
      ],
      "move": 1,
      "sense": 1,
      "sound": 1,
      "door": 0
    },
    {
      "c": [
        4104,
        1350,
        4052,
        1344
      ],
      "move": 1,
      "sense": 1,
      "sound": 1,
      "door": 0
    },
    {
      "c": [
        4052,
        1649,
        4104,
        1642
      ],
      "move": 1,
      "sense": 1,
      "sound": 1,
      "door": 0
    },
    {
      "c": [
        4091,
        1646,
        4140,
        1626
      ],
      "move": 1,
      "sense": 1,
      "sound": 1,
      "door": 0
    },
    {
      "c": [
        4129,
        1632,
        4171,
        1600
      ],
      "move": 1,
      "sense": 1,
      "sound": 1,
      "door": 0
    },
    {
      "c": [
        4162,
        1609,
        4194,
        1567
      ],
      "move": 1,
      "sense": 1,
      "sound": 1,
      "door": 0
    },
    {
      "c": [
        4187,
        1578,
        4208,
        1530
      ],
      "move": 1,
      "sense": 1,
      "sound": 1,
      "door": 0
    },
    {
      "c": [
        4204,
        1542,
        4211,
        1490
      ],
      "move": 1,
      "sense": 1,
      "sound": 1,
      "door": 0
    },
    {
      "c": [
        4065,
        287,
        3972,
        299
      ],
      "move": 1,
      "sense": 1,
      "sound": 1,
      "door": 0
    },
    {
      "c": [
        3986,
        296,
        3900,
        331
      ],
      "move": 1,
      "sense": 1,
      "sound": 1,
      "door": 0
    },
    {
      "c": [
        3912,
        324,
        3838,
        381
      ],
      "move": 1,
      "sense": 1,
      "sound": 1,
      "door": 0
    },
    {
      "c": [
        3847,
        371,
        3791,
        446
      ],
      "move": 1,
      "sense": 1,
      "sound": 1,
      "door": 0
    },
    {
      "c": [
        3797,
        433,
        3762,
        520
      ],
      "move": 1,
      "sense": 1,
      "sound": 1,
      "door": 0
    },
    {
      "c": [
        3765,
        506,
        3753,
        599
      ],
      "move": 1,
      "sense": 1,
      "sound": 1,
      "door": 0
    },
    {
      "c": [
        4363,
        599,
        4351,
        506
      ],
      "move": 1,
      "sense": 1,
      "sound": 1,
      "door": 0
    },
    {
      "c": [
        4355,
        520,
        4319,
        433
      ],
      "move": 1,
      "sense": 1,
      "sound": 1,
      "door": 0
    },
    {
      "c": [
        4326,
        446,
        4269,
        371
      ],
      "move": 1,
      "sense": 1,
      "sound": 1,
      "door": 0
    },
    {
      "c": [
        4279,
        381,
        4205,
        324
      ],
      "move": 1,
      "sense": 1,
      "sound": 1,
      "door": 0
    },
    {
      "c": [
        4217,
        331,
        4130,
        296
      ],
      "move": 1,
      "sense": 1,
      "sound": 1,
      "door": 0
    },
    {
      "c": [
        4144,
        299,
        4051,
        287
      ],
      "move": 1,
      "sense": 1,
      "sound": 1,
      "door": 0
    },
    {
      "c": [
        4051,
        897,
        4144,
        885
      ],
      "move": 1,
      "sense": 1,
      "sound": 1,
      "door": 0
    },
    {
      "c": [
        4130,
        888,
        4217,
        853
      ],
      "move": 1,
      "sense": 1,
      "sound": 1,
      "door": 0
    },
    {
      "c": [
        4205,
        860,
        4279,
        803
      ],
      "move": 1,
      "sense": 1,
      "sound": 1,
      "door": 0
    },
    {
      "c": [
        4269,
        813,
        4326,
        738
      ],
      "move": 1,
      "sense": 1,
      "sound": 1,
      "door": 0
    },
    {
      "c": [
        4319,
        751,
        4355,
        664
      ],
      "move": 1,
      "sense": 1,
      "sound": 1,
      "door": 0
    },
    {
      "c": [
        4351,
        678,
        4363,
        585
      ],
      "move": 1,
      "sense": 1,
      "sound": 1,
      "door": 0
    }
  ],
  "img": null,
  "foreground": null
}